{
  "questions": [
    {
      "id": 1,
      "question": "پایتخت ایران کدام شهر است؟",
      "options": ["تهران", "اصفهان", "شیراز", "مشهد"],
      "correct": 0
    },
    {
      "id": 2,
      "question": "کدام زبان برنامه‌نویسی برای توسعه front-end استفاده می‌شود؟",
      "options": ["Python", "JavaScript", "Java", "C++"],
      "correct": 1
    },
    {
      "id": 3,
      "question": "بزرگترین سیاره منظومه شمسی کدام است؟",
      "options": ["زمین", "مریخ", "مشتری", "زحل"],
      "correct": 2
    },
    {
      "id": 4,
      "question": "کدام یک از موارد زیر یک فریمورک CSS است؟",
      "options": ["React", "Bootstrap", "Django", "Node.js"],
      "correct": 1
    },
    {
      "id": 5,
      "question": "عدد باینری 1010 معادل چه عددی در مبنای 10 است؟",
      "options": ["8", "10", "12", "14"],
      "correct": 1
    },
    {
      "id": 6,
      "question": "کدام پروتکل برای بارگذاری ایمن صفحات وب استفاده می‌شود؟",
      "options": ["FTP", "HTTP", "HTTPS", "SMTP"],
      "correct": 2
    },
    {
      "id": 7,
      "question": "Unit Testing مربوط به کدام مرحله از توسعه نرم‌افزار است؟",
      "options": ["Design", "Testing", "Deployment", "Maintenance"],
      "correct": 1
    },
    {
      "id": 8,
      "question": "کدام یک از موارد زیر یک پایگاه داده NoSQL است؟",
      "options": ["MySQL", "PostgreSQL", "MongoDB", "Oracle"],
      "correct": 2
    },
    {
      "id": 9,
      "question": "CSS مخفف چیست؟",
      "options": ["Computer Style Sheets", "Creative Style System", "Cascading Style Sheets", "Colorful Style Sheets"],
      "correct": 2
    },
    {
      "id": 10,
      "question": "کدام تگ HTML برای ایجاد لیست مرتب استفاده می‌شود؟",
      "options": ["<ul>", "<ol>", "<li>", "<list>"],
      "correct": 1
    },
    {
      "id": 11,
      "question": "کدام شرکت سیستم عامل iOS را توسعه داده است؟",
      "options": ["Google", "Microsoft", "Apple", "Samsung"],
      "correct": 2
    },
    {
      "id": 12,
      "question": "پایتون یک زبان برنامه‌نویسی ________ است.",
      "options": ["کامپایلری", "مفسری", "ماشینی", "سمبلیک"],
      "correct": 1
    },
    {
      "id": 13,
      "question": "کدام یک از موارد زیر یک سیستم کنترل نسخه است؟",
      "options": ["Git", "MySQL", "Photoshop", "Excel"],
      "correct": 0
    },
    {
      "id": 14,
      "question": "API مخفف چیست؟",
      "options": ["Application Programming Interface", "Advanced Programming Interface", "Automated Programming Interface", "Application Process Integration"],
      "correct": 0
    },
    {
      "id": 15,
      "question": "کدام یک از رنگ‌های زیر یک رنگ اصلی است؟",
      "options": ["سبز", "بنفش", "نارنجی", "قرمز"],
      "correct": 3
    },
    {
      "id": 16,
      "question": "طولانی‌ترین رود جهان کدام است؟",
      "options": ["آمازون", "نیل", "میسیسیپی", "یانگتسه"],
      "correct": 1
    },
    {
      "id": 17,
      "question": "کدام عنصر شیمیایی با نماد O نشان داده می‌شود؟",
      "options": ["طلا", "اکسیژن", "نقره", "مس"],
      "correct": 1
    },
    {
      "id": 18,
      "question": "کدام کشور بیشترین جمعیت را در جهان دارد؟",
      "options": ["هند", "آمریکا", "چین", "روسیه"],
      "correct": 2
    },
    {
      "id": 19,
      "question": "سختی الماس در مقیاس موس چند است؟",
      "options": ["7", "8", "9", "10"],
      "correct": 3
    },
    {
      "id": 20,
      "question": "کدام سیاره به سیاره سرخ معروف است؟",
      "options": ["زهره", "مریخ", "مشتری", "زحل"],
      "correct": 1
    },
    {
      "id": 21,
      "question": "سرعت نور در خلا تقریباً چقدر است؟",
      "options": ["300,000 km/s", "150,000 km/s", "500,000 km/s", "1,000,000 km/s"],
      "correct": 0
    },
    {
      "id": 22,
      "question": "کدام یک از موارد زیر یک مرورگر وب نیست؟",
      "options": ["Chrome", "Firefox", "Photoshop", "Safari"],
      "correct": 2
    },
    {
      "id": 23,
      "question": "پایتخت ژاپن کدام شهر است؟",
      "options": ["شانگهای", "سئول", "توکیو", "پکن"],
      "correct": 2
    },
    {
      "id": 24,
      "question": "کدام حیوان بزرگ‌ترین حیوان خشکی است؟",
      "options": ["فیل", "زرافه", "کرگدن", "اسب آبی"],
      "correct": 0
    },
    {
      "id": 25,
      "question": "HTML مخفف چیست؟",
      "options": ["Hyper Text Markup Language", "High Tech Modern Language", "Hyper Transfer Markup Language", "Home Tool Markup Language"],
      "correct": 0
    },
    {
      "id": 26,
      "question": "کدام یک از موارد زیر یک سیستم عامل است؟",
      "options": ["Photoshop", "Linux", "Excel", "Word"],
      "correct": 1
    },
    {
      "id": 27,
      "question": "عدد 101 در مبنای 2 معادل چه عددی در مبنای 10 است؟",
      "options": ["3", "4", "5", "6"],
      "correct": 2
    },
    {
      "id": 28,
      "question": "کدام کشور به کشور هزار جزیره معروف است؟",
      "options": ["مالدیو", "اندونزی", "فیلیپین", "ژاپن"],
      "correct": 1
    },
    {
      "id": 29,
      "question": "کدام گاز بیشترین سهم را در اتمسفر زمین دارد؟",
      "options": ["اکسیژن", "نیتروژن", "دی‌اکسید کربن", "آرگون"],
      "correct": 1
    },
    {
      "id": 30,
      "question": "واکنش شیمیایی بین اسید و باز چه نام دارد؟",
      "options": ["اکسیداسیون", "خنثی‌سازی", "احتراق", "تجزیه"],
      "correct": 1
    },
    {
      "id": 31,
      "question": "کدام یک از سیارات حلقه دارد؟",
      "options": ["مریخ", "زهره", "زحل", "عطارد"],
      "correct": 2
    },
    {
      "id": 32,
      "question": "کدام عنصر شیمیایی با نماد Au نشان داده می‌شود؟",
      "options": ["نقره", "آلومینیوم", "طلا", "آرسنیک"],
      "correct": 2
    },
    {
      "id": 33,
      "question": "سریع‌ترین حیوان خشکی کدام است؟",
      "options": ["شیر", "یوزپلنگ", "آهو", "گرگ"],
      "correct": 1
    },
    {
      "id": 34,
      "question": "کدام یک از موارد زیر یک زبان برنامه‌نویسی است؟",
      "options": ["HTML", "CSS", "Java", "XML"],
      "correct": 2
    },
    {
      "id": 35,
      "question": "بلندترین کوه جهان چه نام دارد؟",
      "options": ["K2", "آناپورنا", "اورست", "ماکالو"],
      "correct": 2
    },
    {
      "id": 36,
      "question": "کدام یک از موارد زیر یک واحد اندازه‌گیری دما است؟",
      "options": ["کیلوگرم", "سانتی‌متر", "سلسیوس", "لیتر"],
      "correct": 2
    },
    {
      "id": 37,
      "question": "پایتخت فرانسه کدام شهر است؟",
      "options": ["لندن", "برلین", "پاریس", "مادرید"],
      "correct": 2
    },
    {
      "id": 38,
      "question": "کدام حیوان نماد استرالیا است؟",
      "options": ["کانگورو", "کوآلا", "شترمرغ", "پاندای"],
      "correct": 0
    },
    {
      "id": 39,
      "question": "کدام یک از موارد زیر یک عدد اول است؟",
      "options": ["1", "4", "9", "17"],
      "correct": 3
    },
    {
      "id": 40,
      "question": "کدام سیاره نزدیک‌ترین سیاره به خورشید است؟",
      "options": ["زهره", "مریخ", "عطارد", "زمین"],
      "correct": 2
    },
    {
      "id": 41,
      "question": "RAM مخفف چیست؟",
      "options": ["Random Access Memory", "Read Only Memory", "Rapid Access Memory", "Random Active Memory"],
      "correct": 0
    },
    {
      "id": 42,
      "question": "کدام یک از نویسندگان زیر ایرانی است؟",
      "options": ["شکسپیر", "هوگو", "حافظ", "داستایفسکی"],
      "correct": 2
    },
    {
      "id": 43,
      "question": "در یک مثلث قائم‌الزاویه، وتر مقابل به کدام زاویه است؟",
      "options": ["زاویه حاده", "زاویه قائمه", "زاویه منفرجه", "هیچکدام"],
      "correct": 1
    },
    {
      "id": 44,
      "question": "کدام کشور به کشور آفتاب تابان معروف است؟",
      "options": ["چین", "هند", "ژاپن", "تایلند"],
      "correct": 2
    },
    {
      "id": 45,
      "question": "کدام گاز برای تنفس انسان ضروری است؟",
      "options": ["نیتروژن", "اکسیژن", "هیدروژن", "دی‌اکسید کربن"],
      "correct": 1
    },
    {
      "id": 46,
      "question": "مخترع تلفن کیست؟",
      "options": ["ادیسون", "گراهام بل", "انیشتین", "نیوتن"],
      "correct": 1
    },
    {
      "id": 47,
      "question": "کدام حیوان بزرگ‌ترین پستاندار جهان است؟",
      "options": ["فیل", "نهنگ آبی", "زرافه", "کرگدن"],
      "correct": 1
    },
    {
      "id": 48,
      "question": "کدام یک از موارد زیر یک عدد گویا است؟",
      "options": ["π", "e", "√2", "0.5"],
      "correct": 3
    },
    {
      "id": 49,
      "question": "پایتخت ایتالیا کدام شهر است؟",
      "options": ["میلان", "ونیز", "رم", "فلورانس"],
      "correct": 2
    },
    {
      "id": 50,
      "question": "کدام سیاره بیشترین قمر را دارد؟",
      "options": ["مریخ", "مشتری", "زحل", "اورانوس"],
      "correct": 2
    },
    {
      "id": 51,
      "question": "CPU مخفف چیست؟",
      "options": ["Central Processing Unit", "Computer Processing Unit", "Central Program Unit", "Computer Program Unit"],
      "correct": 0
    },
    {
      "id": 52,
      "question": "کدام یک از شاعران زیر معروف به 'شاعر شرق' است؟",
      "options": ["حافظ", "سعدی", "مولوی", "اقبال لاهوری"],
      "correct": 3
    },
    {
      "id": 53,
      "question": "مساحت دایره با چه فرمولی محاسبه می‌شود؟",
      "options": ["2πr", "πr²", "πd", "2πr²"],
      "correct": 1
    },
    {
      "id": 54,
      "question": "کدام کشور به کشور کانگوروها معروف است؟",
      "options": ["نیوزلند", "استرالیا", "آفریقای جنوبی", "آرژانتین"],
      "correct": 1
    },
    {
      "id": 55,
      "question": "کدام گاز باعث اثر گلخانه‌ای می‌شود؟",
      "options": ["اکسیژن", "نیتروژن", "دی‌اکسید کربن", "هیدروژن"],
      "correct": 2
    },
    {
      "id": 56,
      "question": "مخترع برق کیست؟",
      "options": ["انیشتین", "ادیسون", "نیوتن", "گالیله"],
      "correct": 1
    },
    {
      "id": 57,
      "question": "کدام حیوان سریع‌ترین پرنده جهان است؟",
      "options": ["عقاب", "شاهین", "قرقی", "پرستو"],
      "correct": 1
    },
    {
      "id": 58,
      "question": "کدام یک از اعداد زیر بر 3 بخشپذیر است؟",
      "options": ["14", "17", "21", "25"],
      "correct": 2
    },
    {
      "id": 59,
      "question": "پایتخت اسپانیا کدام شهر است؟",
      "options": ["بارسلون", "والنسیا", "مادرید", "سیویل"],
      "correct": 2
    },
    {
      "id": 60,
      "question": "کدام سیاره دارای حیات است؟",
      "options": ["مریخ", "زهره", "زمین", "مشتری"],
      "correct": 2
    },
    {
      "id": 61,
      "question": "HTTP مخفف چیست؟",
      "options": ["Hyper Text Transfer Protocol", "High Tech Transfer Protocol", "Hyper Transfer Text Protocol", "Home Tool Transfer Protocol"],
      "correct": 0
    },
    {
      "id": 62,
      "question": "کدام یک از دانشمندان زیر نظریه نسبیت را ارائه داد؟",
      "options": ["نیوتن", "انیشتین", "گالیله", "کپلر"],
      "correct": 1
    },
    {
      "id": 63,
      "question": "محیط مربع با چه فرمولی محاسبه می‌شود؟",
      "options": ["a²", "4a", "2a", "a×b"],
      "correct": 1
    },
    {
      "id": 64,
      "question": "کدام کشور به کشور برزیل آمریکای جنوبی معروف است؟",
      "options": ["آرژانتین", "برزیل", "پرو", "کلمبیا"],
      "correct": 1
    },
    {
      "id": 65,
      "question": "کدام گاز در لامپ‌های نئون استفاده می‌شود؟",
      "options": ["هلیوم", "نئون", "آرگون", "کریپتون"],
      "correct": 1
    },
    {
      "id": 66,
      "question": "مخترع رادیو کیست؟",
      "options": ["ادیسون", "مارکونی", "انیشتین", "نیوتن"],
      "correct": 1
    },
    {
      "id": 67,
      "question": "کدام حیوان بزرگ‌ترین خزنده است؟",
      "options": ["مار پایتون", "تمساح", "اژدهای کومودو", "لاک‌پشت غول‌پیکر"],
      "correct": 1
    },
    {
      "id": 68,
      "question": "کدام یک از اعداد زیر عددی اول است؟",
      "options": ["15", "21", "29", "33"],
      "correct": 2
    },
    {
      "id": 69,
      "question": "پایتخت کانادا کدام شهر است؟",
      "options": ["تورنتو", "ونکوور", "اوتاوا", "مونترال"],
      "correct": 2
    },
    {
      "id": 70,
      "question": "کدام سیاره سردترین سیاره منظومه شمسی است؟",
      "options": ["مریخ", "مشتری", "نپتون", "اورانوس"],
      "correct": 2
    },
    {
      "id": 71,
      "question": "SQL مخفف چیست؟",
      "options": ["Structured Query Language", "Simple Query Language", "Standard Query Language", "System Query Language"],
      "correct": 0
    },
    {
      "id": 72,
      "question": "کدام یک از فیلسوفان زیر یونانی بود؟",
      "options": ["کانت", "افلاطون", "دکارت", "هگل"],
      "correct": 1
    },
    {
      "id": 73,
      "question": "حجم مکعب با چه فرمولی محاسبه می‌شود؟",
      "options": ["a²", "a³", "2a", "3a"],
      "correct": 1
    },
    {
      "id": 74,
      "question": "کدام کشور به کشور هزار دریاچه معروف است؟",
      "options": ["کانادا", "فنلاند", "نروژ", "سوئد"],
      "correct": 1
    },
    {
      "id": 75,
      "question": "کدام گاز در بادکنک‌ها استفاده می‌شود؟",
      "options": ["هیدروژن", "هلیوم", "نیتروژن", "اکسیژن"],
      "correct": 1
    },
    {
      "id": 76,
      "question": "مخترع چاپ کیست؟",
      "options": ["گوتنبرگ", "ادیسون", "داوینچی", "گالیله"],
      "correct": 0
    },
    {
      "id": 77,
      "question": "کدام حیوان کندروترین حیوان جهان است؟",
      "options": ["لاک‌پشت", "کوالا", "تنبل", "حلزون"],
      "correct": 2
    },
    {
      "id": 78,
      "question": "کدام یک از اعداد زیر بر 5 بخشپذیر است؟",
      "options": ["12", "18", "25", "33"],
      "correct": 2
    },
    {
      "id": 79,
      "question": "پایتخت آلمان کدام شهر است؟",
      "options": ["هامبورگ", "مونیخ", "برلین", "فرانکفورت"],
      "correct": 2
    },
    {
      "id": 80,
      "question": "کدام سیاره را 'ستاره صبح' می‌نامند؟",
      "options": ["مریخ", "زهره", "عطارد", "مشتری"],
      "correct": 1
    },
    {
      "id": 81,
      "question": "URL مخفف چیست؟",
      "options": ["Uniform Resource Locator", "Universal Resource Locator", "Uniform Reference Locator", "Universal Reference Locator"],
      "correct": 0
    },
    {
      "id": 82,
      "question": "کدام یک از نقاشان زیر هلندی بود؟",
      "options": ["ون گوگ", "پیکاسو", "داوینچی", "مونه"],
      "correct": 0
    },
    {
      "id": 83,
      "question": "مساحت مثلث با چه فرمولی محاسبه می‌شود؟",
      "options": ["½ × قاعده × ارتفاع", "قاعده × ارتفاع", "½ × محیط", "مجموع اضلاع"],
      "correct": 0
    },
    {
      "id": 84,
      "question": "کدام کشور به کشور اژدهای زرد معروف است؟",
      "options": ["ژاپن", "چین", "کره جنوبی", "ویتنام"],
      "correct": 1
    },
    {
      "id": 85,
      "question": "کدام گاز در کپسول‌های آتش‌نشانی استفاده می‌شود؟",
      "options": ["اکسیژن", "نیتروژن", "دی‌اکسید کربن", "هلیوم"],
      "correct": 2
    },
    {
      "id": 86,
      "question": "مخترع تلسکوپ کیست؟",
      "options": ["گالیله", "نیوتن", "کپلر", "هابل"],
      "correct": 0
    },
    {
      "id": 87,
      "question": "کدام حیوان بزرگ‌ترین پرنده جهان است؟",
      "options": ["عقاب", "شترمرغ", "قو", "پلیکان"],
      "correct": 1
    },
    {
      "id": 88,
      "question": "کدام یک از اعداد زیر بر 9 بخشپذیر است؟",
      "options": ["18", "24", "30", "36"],
      "correct": 0
    },
    {
      "id": 89,
      "question": "پایتخت روسیه کدام شهر است؟",
      "options": ["سن پترزبورگ", "مسکو", "کازان", "نووسیبیرسک"],
      "correct": 1
    },
    {
      "id": 90,
      "question": "کدام سیاره را 'سیاره آبی' می‌نامند؟",
      "options": ["زمین", "نپتون", "اورانوس", "زحل"],
      "correct": 0
    },
    {
      "id": 91,
      "question": "VPN مخفف چیست؟",
      "options": ["Virtual Private Network", "Virtual Public Network", "Verified Private Network", "Verified Public Network"],
      "correct": 0
    },
    {
      "id": 92,
      "question": "کدام یک از آهنگسازان زیر آلمانی بود؟",
      "options": ["بتهوون", "موتزارت", "چایکوفسکی", "باخ"],
      "correct": 0
    },
    {
      "id": 93,
      "question": "محیط دایره با چه فرمولی محاسبه می‌شود؟",
      "options": ["πr", "2πr", "πr²", "πd²"],
      "correct": 1
    },
    {
      "id": 94,
      "question": "کدام کشور به کشور کوهستان‌های سفید معروف است؟",
      "options": ["سوئیس", "نپال", "اتریش", "نیوزلند"],
      "correct": 0
    },
    {
      "id": 95,
      "question": "کدام گاز در صنایع غذایی برای بسته‌بندی استفاده می‌شود؟",
      "options": ["اکسیژن", "نیتروژن", "هیدروژن", "هلیوم"],
      "correct": 1
    },
    {
      "id": 96,
      "question": "مخترع پنی‌سیلین کیست؟",
      "options": ["پاستور", "فلمینگ", "کوری", "انیشتین"],
      "correct": 1
    },
    {
      "id": 97,
      "question": "کدام حیوان بزرگ‌ترین ماهی جهان است؟",
      "options": ["نهنگ کوسه", "کوسه سفید", "مارلین", "پرتو"],
      "correct": 0
    },
    {
      "id": 98,
      "question": "کدام یک از اعداد زیر بر 11 بخشپذیر است؟",
      "options": ["22", "33", "44", "همه موارد"],
      "correct": 3
    },
    {
      "id": 99,
      "question": "پایتخت ترکیه کدام شهر است؟",
      "options": ["استانبول", "آنکارا", "ازمیر", "بورسا"],
      "correct": 1
    },
    {
      "id": 100,
      "question": "کدام سیاره کوچک‌ترین سیاره منظومه شمسی است؟",
      "options": ["مریخ", "عطارد", "زهره", "پلوتو"],
      "correct": 1
    }
  ]
}